mmcli/helper.py
mmcli/mmcli.py
mmcli/mmclient.py
mmcli-1.1.dist-info/LICENSE
mmcli-1.1.dist-info/METADATA
mmcli-1.1.dist-info/WHEEL
mmcli-1.1.dist-info/top_level.txt
mmcli-1.1.dist-info/RECORD
