Metadata-Version: 2.1
Name: mmcli
Version: 1.1
Summary: Cli client for mmdok
Home-page: https://github.com/emagnca/mmcli
Author: Magnus Carlhammar
Author-email: mcarlhammar@gmail.com
License: BSD 2-clause
Platform: UNKNOWN
Classifier: Development Status :: 1 - Planning
Classifier: License :: OSI Approved :: BSD License
Classifier: Programming Language :: Python :: 3 :: Only
Requires-Dist: cmd2
